upkeep/__init__.py
upkeep/commands/__init__.py
upkeep/commands/ecleans.py
upkeep/commands/emerges.py
upkeep/commands/esync.py
upkeep/commands/kernel.py
upkeep/constants.py
upkeep/decorators.py
upkeep/exceptions.py
upkeep/py.typed
upkeep/utils/__init__.py
upkeep/utils/kernel.py
upkeep-1.6.1.dist-info/LICENSE.txt
upkeep-1.6.1.dist-info/METADATA
upkeep-1.6.1.dist-info/WHEEL
upkeep-1.6.1.dist-info/entry_points.txt
upkeep-1.6.1.dist-info/RECORD
