Metadata-Version: 2.3
Name: upkeep
Version: 1.6.1
Summary: Portage update helper commands.
License: MIT
Keywords: administration,command line,gentoo
Author: Andrew Udvare
Author-email: audvare@gmail.com
Requires-Python: >=3.10,<3.14
Classifier: Development Status :: 2 - Pre-Alpha
Classifier: Intended Audience :: Developers
Classifier: License :: OSI Approved :: MIT License
Classifier: Programming Language :: Python
Classifier: Programming Language :: Python :: 3.10
Classifier: Programming Language :: Python :: 3.11
Classifier: Programming Language :: Python :: 3.12
Classifier: Programming Language :: Python :: 3.13
Classifier: Typing :: Typed
Provides-Extra: erdantic
Requires-Dist: click (>=8.1.8,<9.0.0)
Requires-Dist: erdantic (<2.0) ; extra == "erdantic"
Requires-Dist: typing-extensions (>=4.13.1,<5.0.0)
Project-URL: Documentation, https://upkeep.readthedocs.org
Project-URL: Homepage, https://tatsh.github.io/upkeep/
Project-URL: Issues, https://github.com/Tatsh/upkeep/issues
Project-URL: Repository, https://github.com/Tatsh/upkeep
